django_multi_db_relation-0.1.dist-info/DESCRIPTION.rst
django_multi_db_relation-0.1.dist-info/METADATA
django_multi_db_relation-0.1.dist-info/RECORD
django_multi_db_relation-0.1.dist-info/WHEEL
django_multi_db_relation-0.1.dist-info/metadata.json
django_multi_db_relation-0.1.dist-info/top_level.txt
multi_db_relation/__init__.py
multi_db_relation/mixins.py
